{
  "trackId": 0,
  "trackName": "Melbourne Grand Prix Circuit",
  "eventName": "FORMULA 1 LOUIS VUITTON AUSTRALIAN GRAND PRIX",
  "eventName_2026": "FORMULA 1 QATAR AIRWAYS AUSTRALIAN GRAND PRIX",
  "eventName_F2": "FIA FORMULA 2 AUSTRALIAN GRAND PRIX",
  "location": "Melbourne, Australia",
  "year": null,
  "trackLength": 5276,
  "comment": "Generic default variant for Australian GP - works across multiple game versions unless specific year file exists. Values in meters.",
  "turns": [
    {
      "number": 1,
      "trigger": 310,
      "end": 420,
      "name": ""
    },
    {
      "number": 2,
      "trigger": 420,
      "end": 620,
      "name": ""
    },
    {
      "number": 3,
      "trigger": 1050,
      "end": 1175,
      "name": ""
    },
    {
      "number": 4,
      "trigger": 1195,
      "end": 1335,
      "name": ""
    },
    {
      "number": 5,
      "trigger": 1405,
      "end": 1555,
      "name": ""
    },
    {
      "number": 6,
      "trigger": 1825,
      "end": 1945,
      "name": ""
    },
    {
      "number": 7,
      "trigger": 1945,
      "end": 2040,
      "name": ""
    },
    {
      "number": 8,
      "trigger": 2060,
      "end": 2325,
      "name": ""
    },
    {
      "number": 9,
      "trigger": 3240,
      "end": 3375,
      "name": ""
    },
    {
      "number": 10,
      "trigger": 3395,
      "end": 3525,
      "name": ""
    },
    {
      "number": 11,
      "trigger": 4085,
      "end": 4220,
      "name": ""
    },
    {
      "number": 12,
      "trigger": 4340,
      "end": 4520,
      "name": ""
    },
    {
      "number": 13,
      "trigger": 4605,
      "end": 4715,
      "name": ""
    },
    {
      "number": 14,
      "trigger": 4745,
      "end": 4920,
      "name": ""
    }
  ],
  "drsZones":[
    {
      "zone": 1,
      "start": 2549,
      "end": 3264,
      "comment": "Zone 1A - between Turns 8 and 9"
    },
    {
      "zone": 2,
      "start": 3557,
      "end": 4112,
      "comment": "Zone 1B - between Turns 10 and 11"
    },
    {
      "zone": 3,
      "start": 4889,
      "end": 330,
      "comment": "Zone 2A - Start/Finish Straight"
    },
    {
      "zone": 4,
      "start": 585,
      "end": 1055,
      "comment": "Zone 2B - between Turns 2 and 3"
    }
  ]
}
